{
  "$schema": "https://developer.microsoft.com/json-schemas/fabric/item/report/definition/visualContainer/2.0.0/schema.json",
  "name": "card_overweight",
  "position": {
    "x": 20,
    "y": 20,
    "z": 1000,
    "width": 400,
    "height": 120,
    "tabOrder": 1000
  },
  "visual": {
    "visualType": "cardVisual",
    "query": {
      "queryState": {
        "Data": {
          "projections": [
            {
              "field": {
                "Measure": {
                  "Expression": {
                    "SourceRef": {
                      "Entity": "fact_body_measures"
                    }
                  },
                  "Property": "Overweight Plus Rate"
                }
              },
              "queryRef": "fact_body_measures.Overweight Plus Rate",
              "nativeQueryRef": "Overweight Plus Rate"
            }
          ]
        }
      }
    },
    "drillFilterOtherVisuals": true
  }
}